DateTime/DateTime.py
DateTime/DateTime.txt
DateTime/__init__.py
DateTime/interfaces.py
DateTime/pytz.txt
DateTime/pytz_support.py
DateTime/tests/__init__.py
DateTime/tests/julian_testdata.txt
DateTime/tests/test_datetime.py
DateTime-5.2.dist-info/LICENSE.txt
DateTime-5.2.dist-info/METADATA
DateTime-5.2.dist-info/WHEEL
DateTime-5.2.dist-info/top_level.txt
DateTime-5.2.dist-info/RECORD
